{"recettes": [
    {"name":"Matin Ski",
       "ingredients": [
            { "name": "Confitures", "qty":15, "unit":"g" },
            { "name": "Lait", "qty":0.1, "unit":"L", "_comment": "pas bcp de gens en prennent" },
            { "name": "Nutella", "qty":15, "unit":"g" },
            { "name": "Jus de fruits", "qty": 0.2, "unit":"L" },
            { "name": "Café moulu" }
        ]
    },
    {"name":"Matin Kinzout",
       "ingredients": [
            { "name": "Nutella", "qty":15, "unit":"g" },
            { "name": "Barre bretonne / Quatre Quart"},
            { "name": "Jus de fruits", "qty": 0.2, "unit":"L" },
            { "name": "Coca Zéro"},
            { "name": "Café moulu"}
        ]
    }
]
}

